README.rst
setup.py
pyveu/__init__.py
pyveu/si.py
pyveu.egg-info/PKG-INFO
pyveu.egg-info/SOURCES.txt
pyveu.egg-info/dependency_links.txt
pyveu.egg-info/requires.txt
pyveu.egg-info/top_level.txt
pyveu/tests/__init__.py
pyveu/tests/test_arithmetic_history.py
pyveu/tests/test_math.py
pyveu/tests/test_math_function.py
pyveu/tests/test_misc.py
pyveu/tests/test_modifiable_named.py
pyveu/tests/test_named.py
pyveu/tests/test_prefix.py
pyveu/tests/test_quantity.py
pyveu/tests/test_si.py
pyveu/tests/test_system_affiliated.py
pyveu/tests/test_unit.py
pyveu/tests/test_unit_system.py